{
    "Test": "This is a test",
    "GameObjects": [
        {
            "name": "Scene",
            "GameObject id": 1869177169,
            "components": [
                {
                    "Type": 0,
                    "Position": [
                        0,
                        0,
                        0
                    ],
                    "Rotation": [
                        0,
                        0,
                        0,
                        1
                    ],
                    "Scale": [
                        1,
                        1,
                        1
                    ]
                }
            ]
        },
        {
            "name": "Camera",
            "GameObject id": 1908234550,
            "Parent id": 1869177169,
            "components": [
                {
                    "Type": 0,
                    "Position": [
                        0,
                        0,
                        0
                    ],
                    "Rotation": [
                        0,
                        0,
                        0,
                        1
                    ],
                    "Scale": [
                        1,
                        1,
                        1
                    ]
                },
                {
                    "Type": 3,
                    "Vertical FOV": 40,
                    "Horizontal FOV": 2.3008880615234375,
                    "Far Plane Distance": 300,
                    "Near Plane Distance": 0.10000000149011612
                }
            ]
        },
        {
            "name": "BakerHouse",
            "GameObject id": 1379889908,
            "Parent id": 1869177169,
            "components": [
                {
                    "Type": 0,
                    "Position": [
                        0,
                        0,
                        0
                    ],
                    "Rotation": [
                        -0.38383650779724121,
                        -0.38554060459136963,
                        -0.59199213981628418,
                        -0.59462028741836548
                    ],
                    "Scale": [
                        1,
                        1,
                        1
                    ]
                }
            ]
        },
        {
            "name": "Chimney",
            "GameObject id": 1472346596,
            "Parent id": 1379889908,
            "components": [
                {
                    "Type": 0,
                    "Position": [
                        0,
                        0,
                        0
                    ],
                    "Rotation": [
                        0,
                        0,
                        0,
                        1
                    ],
                    "Scale": [
                        0.99999934434890747,
                        0.99999934434890747,
                        0.99999934434890747
                    ]
                },
                {
                    "Type": 1,
                    "Mesh Path": "Library\/Meshes\/Untitled.001.elpepe"
                },
                {
                    "Type": 2,
                    "Material Path": "Library\/Materials\/Baker_house.dds"
                }
            ]
        },
        {
            "name": "Baker_house",
            "GameObject id": 1857350726,
            "Parent id": 1379889908,
            "components": [
                {
                    "Type": 0,
                    "Position": [
                        0,
                        0,
                        0
                    ],
                    "Rotation": [
                        0,
                        0,
                        0,
                        1
                    ],
                    "Scale": [
                        0.99999934434890747,
                        0.99999934434890747,
                        0.99999934434890747
                    ]
                },
                {
                    "Type": 1,
                    "Mesh Path": "Library\/Meshes\/Untitled.elpepe"
                },
                {
                    "Type": 2,
                    "Material Path": "Library\/Materials\/Baker_house.dds"
                }
            ]
        }
    ]
}